README.md
cusbase64.py
setup.py
cusbase64.egg-info/PKG-INFO
cusbase64.egg-info/SOURCES.txt
cusbase64.egg-info/dependency_links.txt
cusbase64.egg-info/entry_points.txt
cusbase64.egg-info/not-zip-safe
cusbase64.egg-info/top_level.txt