Metadata-Version: 2.1
Name: cusbase64
Version: 0.2
Summary: Customized base64 algorithm
Home-page: https://github.com/zoemurmure/CusBase64
Author: zoemurmure
Author-email: zoemurmure@gmail.com
License: UNKNOWN
Platform: UNKNOWN
Classifier: Programming Language :: Python :: 3
Classifier: License :: OSI Approved :: MIT License
